ssc/__init__.py
ssc/cli.py
ssc/auth/__init__.py
ssc/auth/auth.py
ssc/links/__init__.py
ssc/links/checker.py
ssc/links/saver.py
webpages_validator_ssc-0.2.2.dist-info/LICENSE.md
webpages_validator_ssc-0.2.2.dist-info/METADATA
webpages_validator_ssc-0.2.2.dist-info/WHEEL
webpages_validator_ssc-0.2.2.dist-info/entry_points.txt
webpages_validator_ssc-0.2.2.dist-info/top_level.txt
webpages_validator_ssc-0.2.2.dist-info/RECORD
