Metadata-Version: 2.2
Name: webpages-validator-ssc
Version: 0.2.2
Summary: A simple command-line utility for checking a webpage.
Author-email: Ildar Gaziev <ildar@gaziev.info>
License: MIT
Project-URL: Homepage, https://github.com/ildar-gaziev/simple-site-checker
Project-URL: repository, https://github.com/ildar-gaziev/simple-site-checker
Requires-Python: >=3.6
License-File: LICENSE.md
